soggy_box/__init__.py
soggy_box/main.py
soos_soggy_box-1.0.1.dist-info/LICENSE
soos_soggy_box-1.0.1.dist-info/METADATA
soos_soggy_box-1.0.1.dist-info/WHEEL
soos_soggy_box-1.0.1.dist-info/entry_points.txt
soos_soggy_box-1.0.1.dist-info/top_level.txt
soos_soggy_box-1.0.1.dist-info/RECORD
